examples/__init__.py
examples/datasets/__init__.py
examples/datasets/criteo_dataframes.py
examples/dlrm/__init__.py
examples/dlrm/aws_component.py
examples/dlrm/dlrm_main.py
examples/dlrm/data/__init__.py
examples/dlrm/data/dlrm_dataloader.py
examples/dlrm/modules/__init__.py
examples/dlrm/modules/dlrm_train.py
fbgemm_gpu/__init__.py
fbgemm_gpu/batched_unary_embeddings_ops.py
fbgemm_gpu/enums.py
fbgemm_gpu/fbgemm_gpu_py.so
fbgemm_gpu/permute_pooled_embedding_modules.py
fbgemm_gpu/split_embedding_configs.py
fbgemm_gpu/split_embedding_inference_converter.py
fbgemm_gpu/split_table_batched_embeddings_ops.py
fbgemm_gpu/uvm.py
fbgemm_gpu/split_embedding_codegen_lookup_invokers/__init__.py
fbgemm_gpu/split_embedding_codegen_lookup_invokers/lookup_adagrad.py
fbgemm_gpu/split_embedding_codegen_lookup_invokers/lookup_adam.py
fbgemm_gpu/split_embedding_codegen_lookup_invokers/lookup_approx_rowwise_adagrad.py
fbgemm_gpu/split_embedding_codegen_lookup_invokers/lookup_approx_sgd.py
fbgemm_gpu/split_embedding_codegen_lookup_invokers/lookup_args.py
fbgemm_gpu/split_embedding_codegen_lookup_invokers/lookup_lamb.py
fbgemm_gpu/split_embedding_codegen_lookup_invokers/lookup_lars_sgd.py
fbgemm_gpu/split_embedding_codegen_lookup_invokers/lookup_partial_rowwise_adam.py
fbgemm_gpu/split_embedding_codegen_lookup_invokers/lookup_partial_rowwise_lamb.py
fbgemm_gpu/split_embedding_codegen_lookup_invokers/lookup_rowwise_adagrad.py
fbgemm_gpu/split_embedding_codegen_lookup_invokers/lookup_rowwise_weighted_adagrad.py
fbgemm_gpu/split_embedding_codegen_lookup_invokers/lookup_sgd.py
torchrec/__init__.py
torchrec/streamable.py
torchrec/datasets/__init__.py
torchrec/datasets/criteo.py
torchrec/datasets/movielens.py
torchrec/datasets/random.py
torchrec/datasets/utils.py
torchrec/datasets/scripts/__init__.py
torchrec/datasets/scripts/contiguous_preproc_criteo.py
torchrec/datasets/scripts/npy_preproc_criteo.py
torchrec/datasets/test_utils/__init__.py
torchrec/datasets/test_utils/criteo_test_utils.py
torchrec_cpu-0.1.0.dist-info/LICENSE
torchrec_cpu-0.1.0.dist-info/METADATA
torchrec_cpu-0.1.0.dist-info/WHEEL
torchrec_cpu-0.1.0.dist-info/top_level.txt
torchrec_cpu-0.1.0.dist-info/RECORD
